libcasm/composition/__init__.py
libcasm/composition/_composition.cpython-312-aarch64-linux-gnu.so
libcasm/composition/_formation_energy_calculator.py
libcasm/composition/_methods.py
libcasm/include/casm/composition/CompositionCalculator.hh
libcasm/include/casm/composition/CompositionConverter.hh
libcasm/include/casm/composition/composition_space.hh
libcasm/include/casm/composition/io/json/CompositionConverter_json_io.hh
libcasm/lib/libcasm_composition.so
libcasm/share/CASMcode_composition/cmake/CASMcode_compositionConfig.cmake
libcasm/share/CASMcode_composition/cmake/CASMcode_compositionConfigVersion.cmake
libcasm/share/CASMcode_composition/cmake/CASMcode_compositionTargets-release.cmake
libcasm/share/CASMcode_composition/cmake/CASMcode_compositionTargets.cmake
libcasm_composition-2.3.0.dist-info/licenses/LICENSE
libcasm_composition-2.3.0.dist-info/METADATA
libcasm_composition-2.3.0.dist-info/WHEEL
libcasm_composition-2.3.0.dist-info/top_level.txt
libcasm_composition-2.3.0.dist-info/RECORD
