Metadata-Version: 2.4
Name: libcasm-composition
Version: 2.3.0
Summary: CASM composition axes, conversions, and calculations
Author-email: CASM developers <casm-developers@lists.engr.ucsb.edu>
License: LGPL2.1+
Project-URL: Homepage, https://prisms-center.github.io/CASMcode_docs/
Project-URL: Repository, https://github.com/prisms-center/CASMcode_composition
Classifier: Development Status :: 5 - Production/Stable
Classifier: Programming Language :: Python :: 3
Classifier: Programming Language :: C++
Classifier: License :: OSI Approved :: GNU Lesser General Public License v2 or later (LGPLv2+)
Classifier: Topic :: Scientific/Engineering
Requires-Python: <3.15,>=3.10
License-File: LICENSE
Requires-Dist: libcasm-global>=2.3.0
Requires-Dist: numpy
Requires-Dist: tabulate
Dynamic: license-file
